{
   "runs" : [
      {
         "OS" : "linux",
         "abstract" : "Interface to L<https://open-meteo.com> for historical weather data",
         "dir" : "/home/runner/work/Weather-Meteo/Weather-Meteo",
         "finish" : 1780332578.3449,
         "name" : "Weather-Meteo",
         "perl" : "5.40.4",
         "run" : "-e",
         "start" : 1780332560.93428,
         "version" : "0.14"
      },
      {
         "OS" : "linux",
         "abstract" : "Interface to L<https://open-meteo.com> for historical weather data",
         "dir" : "/home/runner/work/Weather-Meteo/Weather-Meteo",
         "finish" : 1780332561.08197,
         "name" : "Weather-Meteo",
         "perl" : "5.40.4",
         "run" : "-e",
         "start" : 1780332561.08184,
         "version" : "0.14"
      },
      {
         "OS" : "linux",
         "abstract" : "Interface to L<https://open-meteo.com> for historical weather data",
         "dir" : "/home/runner/work/Weather-Meteo/Weather-Meteo",
         "finish" : 1780332561.46294,
         "name" : "Weather-Meteo",
         "perl" : "5.40.4",
         "run" : "t/00-load.t",
         "start" : 1780332561.46171,
         "version" : "0.14"
      },
      {
         "OS" : "linux",
         "abstract" : "Interface to L<https://open-meteo.com> for historical weather data",
         "dir" : "/home/runner/work/Weather-Meteo/Weather-Meteo",
         "finish" : 1780332562.03088,
         "name" : "Weather-Meteo",
         "perl" : "5.40.4",
         "run" : "t/10-compile.t",
         "start" : 1780332561.70945,
         "version" : "0.14"
      },
      {
         "OS" : "linux",
         "abstract" : "Interface to L<https://open-meteo.com> for historical weather data",
         "dir" : "/home/runner/work/Weather-Meteo/Weather-Meteo",
         "finish" : 1780332562.45645,
         "name" : "Weather-Meteo",
         "perl" : "5.40.4",
         "run" : "t/20-new.t",
         "start" : 1780332562.28254,
         "version" : "0.14"
      },
      {
         "OS" : "linux",
         "abstract" : "Interface to L<https://open-meteo.com> for historical weather data",
         "dir" : "/home/runner/work/Weather-Meteo/Weather-Meteo",
         "finish" : 1780332562.98778,
         "name" : "Weather-Meteo",
         "perl" : "5.40.4",
         "run" : "t/30-basics.t",
         "start" : 1780332562.91427,
         "version" : "0.14"
      },
      {
         "OS" : "linux",
         "abstract" : "Interface to L<https://open-meteo.com> for historical weather data",
         "dir" : "/home/runner/work/Weather-Meteo/Weather-Meteo",
         "finish" : 1780332563.51226,
         "name" : "Weather-Meteo",
         "perl" : "5.40.4",
         "run" : "t/carp.t",
         "start" : 1780332563.43831,
         "version" : "0.14"
      },
      {
         "OS" : "linux",
         "abstract" : "Interface to L<https://open-meteo.com> for historical weather data",
         "dir" : "/home/runner/work/Weather-Meteo/Weather-Meteo",
         "finish" : 1780332563.82979,
         "name" : "Weather-Meteo",
         "perl" : "5.40.4",
         "run" : "t/comment-spelling.t",
         "start" : 1780332563.82953,
         "version" : "0.14"
      },
      {
         "OS" : "linux",
         "abstract" : "Interface to L<https://open-meteo.com> for historical weather data",
         "dir" : "/home/runner/work/Weather-Meteo/Weather-Meteo",
         "finish" : 1780332564.06067,
         "name" : "Weather-Meteo",
         "perl" : "5.40.4",
         "run" : "t/critic.t",
         "start" : 1780332564.06042,
         "version" : "0.14"
      },
      {
         "OS" : "linux",
         "abstract" : "Interface to L<https://open-meteo.com> for historical weather data",
         "dir" : "/home/runner/work/Weather-Meteo/Weather-Meteo",
         "finish" : 1780332564.71522,
         "name" : "Weather-Meteo",
         "perl" : "5.40.4",
         "run" : "t/edge_cases.t",
         "start" : 1780332564.43917,
         "version" : "0.14"
      },
      {
         "OS" : "linux",
         "abstract" : "Interface to L<https://open-meteo.com> for historical weather data",
         "dir" : "/home/runner/work/Weather-Meteo/Weather-Meteo",
         "finish" : 1780332565.11175,
         "name" : "Weather-Meteo",
         "perl" : "5.40.4",
         "run" : "t/eof.t",
         "start" : 1780332565.11147,
         "version" : "0.14"
      },
      {
         "OS" : "linux",
         "abstract" : "Interface to L<https://open-meteo.com> for historical weather data",
         "dir" : "/home/runner/work/Weather-Meteo/Weather-Meteo",
         "finish" : 1780332565.34443,
         "name" : "Weather-Meteo",
         "perl" : "5.40.4",
         "run" : "t/eol.t",
         "start" : 1780332565.34413,
         "version" : "0.14"
      },
      {
         "OS" : "linux",
         "abstract" : "Interface to L<https://open-meteo.com> for historical weather data",
         "dir" : "/home/runner/work/Weather-Meteo/Weather-Meteo",
         "finish" : 1780332565.91375,
         "name" : "Weather-Meteo",
         "perl" : "5.40.4",
         "run" : "t/extended_tests.t",
         "start" : 1780332565.72676,
         "version" : "0.14"
      },
      {
         "OS" : "linux",
         "abstract" : "Interface to L<https://open-meteo.com> for historical weather data",
         "dir" : "/home/runner/work/Weather-Meteo/Weather-Meteo",
         "finish" : 1780332566.6907,
         "name" : "Weather-Meteo",
         "perl" : "5.40.4",
         "run" : "t/function.t",
         "start" : 1780332566.44206,
         "version" : "0.14"
      },
      {
         "OS" : "linux",
         "abstract" : "Interface to L<https://open-meteo.com> for historical weather data",
         "dir" : "/home/runner/work/Weather-Meteo/Weather-Meteo",
         "finish" : 1780332570.37363,
         "name" : "Weather-Meteo",
         "perl" : "5.40.4",
         "run" : "t/fuzz.t",
         "start" : 1780332567.21356,
         "version" : "0.14"
      },
      {
         "OS" : "linux",
         "abstract" : "Interface to L<https://open-meteo.com> for historical weather data",
         "dir" : "/home/runner/work/Weather-Meteo/Weather-Meteo",
         "finish" : 1780332568.67586,
         "name" : "Weather-Meteo",
         "perl" : "5.40.4",
         "run" : "/opt/hostedtoolcache/perl/5.40.4/x64/bin/fuzz-harness-generator",
         "start" : 1780332567.48807,
         "version" : "0.14"
      },
      {
         "OS" : "linux",
         "abstract" : "Interface to L<https://open-meteo.com> for historical weather data",
         "dir" : "/home/runner/work/Weather-Meteo/Weather-Meteo",
         "finish" : 1780332568.62632,
         "name" : "Weather-Meteo",
         "perl" : "5.40.4",
         "run" : "/opt/hostedtoolcache/perl/5.40.4/x64/bin/prove",
         "start" : 1780332567.69701,
         "version" : "0.14"
      },
      {
         "OS" : "linux",
         "abstract" : "Interface to L<https://open-meteo.com> for historical weather data",
         "dir" : "/home/runner/work/Weather-Meteo/Weather-Meteo",
         "finish" : 1780332568.16744,
         "name" : "Weather-Meteo",
         "perl" : "5.40.4",
         "run" : "/tmp/ENblGjd1Gr",
         "start" : 1780332568.09513,
         "version" : "0.14"
      },
      {
         "OS" : "linux",
         "abstract" : "Interface to L<https://open-meteo.com> for historical weather data",
         "dir" : "/home/runner/work/Weather-Meteo/Weather-Meteo",
         "finish" : 1780332570.27545,
         "name" : "Weather-Meteo",
         "perl" : "5.40.4",
         "run" : "/opt/hostedtoolcache/perl/5.40.4/x64/bin/fuzz-harness-generator",
         "start" : 1780332569.04329,
         "version" : "0.14"
      },
      {
         "OS" : "linux",
         "abstract" : "Interface to L<https://open-meteo.com> for historical weather data",
         "dir" : "/home/runner/work/Weather-Meteo/Weather-Meteo",
         "finish" : 1780332570.22354,
         "name" : "Weather-Meteo",
         "perl" : "5.40.4",
         "run" : "/opt/hostedtoolcache/perl/5.40.4/x64/bin/prove",
         "start" : 1780332569.2526,
         "version" : "0.14"
      },
      {
         "OS" : "linux",
         "abstract" : "Interface to L<https://open-meteo.com> for historical weather data",
         "dir" : "/home/runner/work/Weather-Meteo/Weather-Meteo",
         "finish" : 1780332569.73482,
         "name" : "Weather-Meteo",
         "perl" : "5.40.4",
         "run" : "/tmp/iYlNQQNdTQ",
         "start" : 1780332569.65216,
         "version" : "0.14"
      },
      {
         "OS" : "linux",
         "abstract" : "Interface to L<https://open-meteo.com> for historical weather data",
         "dir" : "/home/runner/work/Weather-Meteo/Weather-Meteo",
         "finish" : 1780332570.97152,
         "name" : "Weather-Meteo",
         "perl" : "5.40.4",
         "run" : "t/integration.t",
         "start" : 1780332570.79481,
         "version" : "0.14"
      },
      {
         "OS" : "linux",
         "abstract" : "Interface to L<https://open-meteo.com> for historical weather data",
         "dir" : "/home/runner/work/Weather-Meteo/Weather-Meteo",
         "finish" : 1780332571.35403,
         "name" : "Weather-Meteo",
         "perl" : "5.40.4",
         "run" : "t/kwalitee.t",
         "start" : 1780332571.35375,
         "version" : "0.14"
      },
      {
         "OS" : "linux",
         "abstract" : "Interface to L<https://open-meteo.com> for historical weather data",
         "dir" : "/home/runner/work/Weather-Meteo/Weather-Meteo",
         "finish" : 1780332572.80511,
         "name" : "Weather-Meteo",
         "perl" : "5.40.4",
         "run" : "t/limiting.t",
         "start" : 1780332571.73267,
         "version" : "0.14"
      },
      {
         "OS" : "linux",
         "abstract" : "Interface to L<https://open-meteo.com> for historical weather data",
         "dir" : "/home/runner/work/Weather-Meteo/Weather-Meteo",
         "finish" : 1780332573.12359,
         "name" : "Weather-Meteo",
         "perl" : "5.40.4",
         "run" : "t/links.t",
         "start" : 1780332573.12332,
         "version" : "0.14"
      },
      {
         "OS" : "linux",
         "abstract" : "Interface to L<https://open-meteo.com> for historical weather data",
         "dir" : "/home/runner/work/Weather-Meteo/Weather-Meteo",
         "finish" : 1780332573.67155,
         "name" : "Weather-Meteo",
         "perl" : "5.40.4",
         "run" : "t/mutant_killers.t",
         "start" : 1780332573.50691,
         "version" : "0.14"
      },
      {
         "OS" : "linux",
         "abstract" : "Interface to L<https://open-meteo.com> for historical weather data",
         "dir" : "/home/runner/work/Weather-Meteo/Weather-Meteo",
         "finish" : 1780332574.04366,
         "name" : "Weather-Meteo",
         "perl" : "5.40.4",
         "run" : "t/no404s.t",
         "start" : 1780332574.0434,
         "version" : "0.14"
      },
      {
         "OS" : "linux",
         "abstract" : "Interface to L<https://open-meteo.com> for historical weather data",
         "dir" : "/home/runner/work/Weather-Meteo/Weather-Meteo",
         "finish" : 1780332574.27986,
         "name" : "Weather-Meteo",
         "perl" : "5.40.4",
         "run" : "t/noplan.t",
         "start" : 1780332574.27957,
         "version" : "0.14"
      },
      {
         "OS" : "linux",
         "abstract" : "Interface to L<https://open-meteo.com> for historical weather data",
         "dir" : "/home/runner/work/Weather-Meteo/Weather-Meteo",
         "finish" : 1780332574.54422,
         "name" : "Weather-Meteo",
         "perl" : "5.40.4",
         "run" : "t/pod-cm.t",
         "start" : 1780332574.54326,
         "version" : "0.14"
      },
      {
         "OS" : "linux",
         "abstract" : "Interface to L<https://open-meteo.com> for historical weather data",
         "dir" : "/home/runner/work/Weather-Meteo/Weather-Meteo",
         "finish" : 1780332574.79187,
         "name" : "Weather-Meteo",
         "perl" : "5.40.4",
         "run" : "t/pod-coverage.t",
         "start" : 1780332574.79157,
         "version" : "0.14"
      },
      {
         "OS" : "linux",
         "abstract" : "Interface to L<https://open-meteo.com> for historical weather data",
         "dir" : "/home/runner/work/Weather-Meteo/Weather-Meteo",
         "finish" : 1780332575.02966,
         "name" : "Weather-Meteo",
         "perl" : "5.40.4",
         "run" : "t/pod-snippets.t",
         "start" : 1780332575.02936,
         "version" : "0.14"
      },
      {
         "OS" : "linux",
         "abstract" : "Interface to L<https://open-meteo.com> for historical weather data",
         "dir" : "/home/runner/work/Weather-Meteo/Weather-Meteo",
         "finish" : 1780332575.29124,
         "name" : "Weather-Meteo",
         "perl" : "5.40.4",
         "run" : "t/pod-spelling.t",
         "start" : 1780332575.29042,
         "version" : "0.14"
      },
      {
         "OS" : "linux",
         "abstract" : "Interface to L<https://open-meteo.com> for historical weather data",
         "dir" : "/home/runner/work/Weather-Meteo/Weather-Meteo",
         "finish" : 1780332575.53889,
         "name" : "Weather-Meteo",
         "perl" : "5.40.4",
         "run" : "t/pod-synopsis.t",
         "start" : 1780332575.53858,
         "version" : "0.14"
      },
      {
         "OS" : "linux",
         "abstract" : "Interface to L<https://open-meteo.com> for historical weather data",
         "dir" : "/home/runner/work/Weather-Meteo/Weather-Meteo",
         "finish" : 1780332575.77819,
         "name" : "Weather-Meteo",
         "perl" : "5.40.4",
         "run" : "t/pod.t",
         "start" : 1780332575.77785,
         "version" : "0.14"
      },
      {
         "OS" : "linux",
         "abstract" : "Interface to L<https://open-meteo.com> for historical weather data",
         "dir" : "/home/runner/work/Weather-Meteo/Weather-Meteo",
         "finish" : 1780332576.04186,
         "name" : "Weather-Meteo",
         "perl" : "5.40.4",
         "run" : "t/port.t",
         "start" : 1780332576.04155,
         "version" : "0.14"
      },
      {
         "OS" : "linux",
         "abstract" : "Interface to L<https://open-meteo.com> for historical weather data",
         "dir" : "/home/runner/work/Weather-Meteo/Weather-Meteo",
         "finish" : 1780332576.28746,
         "name" : "Weather-Meteo",
         "perl" : "5.40.4",
         "run" : "t/strict.t",
         "start" : 1780332576.28716,
         "version" : "0.14"
      },
      {
         "OS" : "linux",
         "abstract" : "Interface to L<https://open-meteo.com> for historical weather data",
         "dir" : "/home/runner/work/Weather-Meteo/Weather-Meteo",
         "finish" : 1780332576.88855,
         "name" : "Weather-Meteo",
         "perl" : "5.40.4",
         "run" : "t/unit.t",
         "start" : 1780332576.67217,
         "version" : "0.14"
      },
      {
         "OS" : "linux",
         "abstract" : "Interface to L<https://open-meteo.com> for historical weather data",
         "dir" : "/home/runner/work/Weather-Meteo/Weather-Meteo",
         "finish" : 1780332577.29096,
         "name" : "Weather-Meteo",
         "perl" : "5.40.4",
         "run" : "t/unused.t",
         "start" : 1780332577.29022,
         "version" : "0.14"
      },
      {
         "OS" : "linux",
         "abstract" : "Interface to L<https://open-meteo.com> for historical weather data",
         "dir" : "/home/runner/work/Weather-Meteo/Weather-Meteo",
         "finish" : 1780332577.54153,
         "name" : "Weather-Meteo",
         "perl" : "5.40.4",
         "run" : "t/vars.t",
         "start" : 1780332577.54125,
         "version" : "0.14"
      },
      {
         "OS" : "linux",
         "abstract" : "Interface to L<https://open-meteo.com> for historical weather data",
         "dir" : "/home/runner/work/Weather-Meteo/Weather-Meteo",
         "finish" : 1780332577.77615,
         "name" : "Weather-Meteo",
         "perl" : "5.40.4",
         "run" : "t/version.t",
         "start" : 1780332577.77587,
         "version" : "0.14"
      },
      {
         "OS" : "linux",
         "abstract" : "Interface to L<https://open-meteo.com> for historical weather data",
         "dir" : "/home/runner/work/Weather-Meteo/Weather-Meteo",
         "finish" : 1780332578.21257,
         "name" : "Weather-Meteo",
         "perl" : "5.40.4",
         "run" : "t/weather.t",
         "start" : 1780332578.14291,
         "version" : "0.14"
      }
   ],
   "summary" : {
      "/opt/hostedtoolcache/perl/5.40.4/x64/bin/fuzz-harness-generator" : {
         "branch" : {
            "covered" : 11,
            "error" : 69,
            "percentage" : 13.75,
            "total" : 80,
            "uncoverable" : 0
         },
         "condition" : {
            "covered" : 5,
            "error" : 25,
            "percentage" : 16.6666666666667,
            "total" : 30,
            "uncoverable" : 0
         },
         "statement" : {
            "covered" : 50,
            "error" : 120,
            "percentage" : 29.4117647058823,
            "total" : 170
         },
         "subroutine" : {
            "covered" : 9,
            "error" : 4,
            "percentage" : 69.2307692307692,
            "total" : 13
         },
         "total" : {
            "covered" : 75,
            "error" : 218,
            "percentage" : 25.5972696245734,
            "total" : 293,
            "uncoverable" : 0
         }
      },
      "/opt/hostedtoolcache/perl/5.40.4/x64/bin/prove" : {
         "branch" : {
            "covered" : 2,
            "error" : 2,
            "percentage" : 50,
            "total" : 4,
            "uncoverable" : 0
         },
         "statement" : {
            "covered" : 14,
            "percentage" : 100,
            "total" : 14
         },
         "subroutine" : {
            "covered" : 4,
            "percentage" : 100,
            "total" : 4
         },
         "total" : {
            "covered" : 20,
            "error" : 2,
            "percentage" : 90.9090909090909,
            "total" : 22,
            "uncoverable" : 0
         }
      },
      "/tmp/ENblGjd1Gr" : {
         "branch" : {
            "covered" : 36,
            "error" : 678,
            "percentage" : 5.04201680672269,
            "total" : 714,
            "uncoverable" : 0
         },
         "condition" : {
            "covered" : 17,
            "error" : 288,
            "percentage" : 5.57377049180327,
            "total" : 305,
            "uncoverable" : 0
         },
         "statement" : {
            "covered" : 188,
            "error" : 994,
            "percentage" : 15.9052453468697,
            "total" : 1182
         },
         "subroutine" : {
            "covered" : 26,
            "error" : 34,
            "percentage" : 43.3333333333333,
            "total" : 60
         },
         "total" : {
            "covered" : 267,
            "error" : 1994,
            "percentage" : 11.8089340999558,
            "total" : 2261,
            "uncoverable" : 0
         }
      },
      "/tmp/iYlNQQNdTQ" : {
         "branch" : {
            "covered" : 94,
            "error" : 704,
            "percentage" : 11.7794486215539,
            "total" : 798,
            "uncoverable" : 0
         },
         "condition" : {
            "covered" : 53,
            "error" : 252,
            "percentage" : 17.3770491803279,
            "total" : 305,
            "uncoverable" : 0
         },
         "statement" : {
            "covered" : 267,
            "error" : 974,
            "percentage" : 21.5149073327961,
            "total" : 1241
         },
         "subroutine" : {
            "covered" : 29,
            "error" : 36,
            "percentage" : 44.6153846153846,
            "total" : 65
         },
         "total" : {
            "covered" : 443,
            "error" : 1966,
            "percentage" : 18.3893731838937,
            "total" : 2409,
            "uncoverable" : 0
         }
      },
      "Total" : {
         "branch" : {
            "covered" : 199,
            "error" : 1457,
            "percentage" : 12.0169082125604,
            "total" : 1656,
            "uncoverable" : 0
         },
         "condition" : {
            "covered" : 122,
            "error" : 568,
            "percentage" : 17.6811594202899,
            "total" : 690,
            "uncoverable" : 0
         },
         "statement" : {
            "covered" : 669,
            "error" : 2089,
            "percentage" : 24.2567077592458,
            "total" : 2758
         },
         "subroutine" : {
            "covered" : 87,
            "error" : 74,
            "percentage" : 54.0372670807453,
            "total" : 161
         },
         "total" : {
            "covered" : 1077,
            "error" : 4188,
            "percentage" : 20.4558404558405,
            "total" : 5265,
            "uncoverable" : 0
         }
      },
      "blib/lib/Weather/Meteo.pm" : {
         "branch" : {
            "covered" : 56,
            "error" : 4,
            "percentage" : 93.3333333333333,
            "total" : 60,
            "uncoverable" : 0
         },
         "condition" : {
            "covered" : 47,
            "error" : 3,
            "percentage" : 94,
            "total" : 50,
            "uncoverable" : 0
         },
         "statement" : {
            "covered" : 150,
            "error" : 1,
            "percentage" : 99.3377483443709,
            "total" : 151
         },
         "subroutine" : {
            "covered" : 19,
            "percentage" : 100,
            "total" : 19
         },
         "total" : {
            "covered" : 272,
            "error" : 8,
            "percentage" : 97.1428571428571,
            "total" : 280,
            "uncoverable" : 0
         }
      }
   }
}
